setup.py
addone/__init__.py
addone/addone.py
addone.egg-info/PKG-INFO
addone.egg-info/SOURCES.txt
addone.egg-info/dependency_links.txt
addone.egg-info/not-zip-safe
addone.egg-info/top_level.txt