Metadata-Version: 1.0
Name: addone
Version: 0.1
Summary: clinical trial information retriver
Home-page: http://github.com/peng/addone
Author: pengyuxupjl
Author-email: 373836911@qq.com
License: MIT
Platform: UNKNOWN
